{
  "grade": "3",
  "field": "De lo Humano y lo Comunitario",
  "ppaNumber": "6",
  "status": "teacher-orientation",
  "officialHorizonStatus": "pending",
  "situatedPedagogicalOrientation": "El PPA 6 propone trabajar ¡Un congreso innovador de salud! mediante productos de cierre, conceptos confirmados y videos directos para reforzar la autoevaluacion.",
  "integratingQuestions": [
    "¿Como se relacionan los tres proyectos academicos del PPA 6 con ¡Un congreso innovador de salud!?",
    "¿Que conceptos necesita dominar el estudiante para explicar su producto final?",
    "¿Como usar el producto final para comunicar una comprension y no solo presentar informacion?"
  ],
  "possibleResonanceQuestion": "¿Que comprension nueva sobre ¡Un congreso innovador de salud! puedes explicar con los productos del PPA 6?",
  "teacherNotes": [
    "Usar los videos directos como detonadores, no como enlaces de busqueda.",
    "Retomar los conceptos confirmados antes de resolver la relacion de columnas y el juego."
  ],
  "projectConnections": [
    {
      "projectId": "de-lo-humano-y-lo-comunitario-3-ppa-6-pa16",
      "projectTitle": "Lo indispensable para una vida saludable",
      "roleInPpa": "Aporta plan de vida activa y saludable al desarrollo del PPA 6.",
      "confirmedConcepts": [
        "Plan de vida activa y saludable",
        "Proyecto de vida",
        "Bienestar",
        "Prevencion",
        "Comunidad"
      ],
      "suggestedConcepts": [
        "Decisiones"
      ],
      "pedagogicalUse": "Video detonador del Proyecto Academico 16: Lo indispensable para una vida saludable"
    },
    {
      "projectId": "de-lo-humano-y-lo-comunitario-3-ppa-6-pa17",
      "projectTitle": "Me cuido, te cuidas y nos cuidamos",
      "roleInPpa": "Aporta actuaciones breves al desarrollo del PPA 6.",
      "confirmedConcepts": [
        "Actuaciones breves",
        "Proyecto de vida",
        "Bienestar",
        "Prevencion",
        "Comunidad"
      ],
      "suggestedConcepts": [
        "Decisiones"
      ],
      "pedagogicalUse": "Video detonador del Proyecto Academico 17: Me cuido, te cuidas y nos cuidamos"
    },
    {
      "projectId": "de-lo-humano-y-lo-comunitario-3-ppa-6-pa18",
      "projectTitle": "Mi comunidad se transforma en ciencia",
      "roleInPpa": "Aporta 3. ¡porque en comunidad hacemos más! al desarrollo del PPA 6.",
      "confirmedConcepts": [
        "3. ¡porque en comunidad hacemos más!",
        "Proyecto de vida",
        "Bienestar",
        "Prevencion",
        "Comunidad"
      ],
      "suggestedConcepts": [
        "Decisiones"
      ],
      "pedagogicalUse": "Video detonador del Proyecto Academico 18: Mi comunidad se transforma en ciencia"
    }
  ]
}
